cyrtranslit/__init__.py
cyrtranslit/cyrtranslit.py
cyrtranslit/mapping.py
cyrtranslit-1.1.dist-info/LICENSE
cyrtranslit-1.1.dist-info/METADATA
cyrtranslit-1.1.dist-info/WHEEL
cyrtranslit-1.1.dist-info/entry_points.txt
cyrtranslit-1.1.dist-info/top_level.txt
cyrtranslit-1.1.dist-info/RECORD
