Metadata-Version: 2.1
Name: cyrtranslit
Version: 1.1
Summary: Bi-directional Cyrillic transliteration. Transliterate Cyrillic script to Latin script and vice versa. Supports transliteration for Bulgarian, Montenegrin, Macedonian, Mongolian, Russian, Serbian, Tajik, and Ukrainian.
Home-page: https://github.com/opendatakosovo/cyrillic-transliteration
Download-URL: https://github.com/opendatakosovo/cyrillic-transliteration/archive/v1.1.tar.gz
Author: Georges Labrèche, Open Data Kosovo
Author-email: georges@tanagraspace.com
License: MIT
Keywords: cyrillic,latin,transliteration,transliterate,cyrtranslit,bulgarian,montenegrin,macedonian,mongolian,russian,serbian,tajik,ukrainian
Classifier: Development Status :: 5 - Production/Stable
Classifier: Intended Audience :: Developers
Classifier: License :: OSI Approved :: MIT License
Classifier: Programming Language :: Python
Classifier: Programming Language :: Python :: 2.7
Classifier: Programming Language :: Python :: 3
Classifier: Programming Language :: Python :: 3.2
Classifier: Programming Language :: Python :: 3.3
Classifier: Programming Language :: Python :: 3.4
Classifier: Programming Language :: Python :: 3.5
Classifier: Programming Language :: Python :: 3.6
Classifier: Programming Language :: Python :: 3.7
Classifier: Programming Language :: Python :: 3.8
License-File: LICENSE
